mtime_fixer/__init__.py
mtime_fixer/__main__.py
mtime_fixer/cli.py
mtime_fixer/core.py
mtime_fixer-1.0.0.dist-info/METADATA
mtime_fixer-1.0.0.dist-info/WHEEL
mtime_fixer-1.0.0.dist-info/top_level.txt
mtime_fixer-1.0.0.dist-info/RECORD
