Metadata-Version: 2.1
Name: mtime-fixer
Version: 1.0.0
Summary: A tool for fixing inconsistent timestamp metadata (atime, ctime, and mtime).
Home-page: https://www.github.com/simsekhalit/mtime-fixer
Author: Halit Şimşek
Author-email: mail.simsekhalit@gmail.com
License: MIT
Keywords: atime,ctime,metadata,mtime
Platform: UNKNOWN
Classifier: Development Status :: 5 - Production/Stable
Classifier: License :: OSI Approved :: MIT License
Classifier: Programming Language :: Python
Classifier: Programming Language :: Python :: 3
Classifier: Programming Language :: Python :: 3.8
Classifier: Programming Language :: Python :: 3.9
Classifier: Programming Language :: Python :: 3.10
Classifier: Programming Language :: Python :: 3.11
Classifier: Programming Language :: Python :: Implementation :: CPython
Classifier: Programming Language :: Python :: Implementation :: PyPy
Classifier: Topic :: System :: Archiving
Requires-Python: >=3.8
